{
  "drive_name": "Documents",
  "name": "International-Shipping-Guide-V1.docx",
  "path": "Knowledge Base/Shipping/International-Shipping-Guide-V1.docx",
  "full_path": "Documents/Knowledge Base/Shipping/International-Shipping-Guide-V1.docx",
  "drive_id": "b!uqgHR9wiN0uomwuRQeJTgVqAfA4bIDRBtstVmpSQbdNFofPisy05Ra0aiz0-Crn4",
  "item_id": "01APWLVA2I6ZIYI5MF5NELT44APJG4LYAC",
  "web_url": "https://ceking.sharepoint.com/sites/AI-Knowledge/_layouts/15/Doc.aspx?sourcedoc=%7B8451F648-8575-48EB-B9F3-807A4DC5E002%7D&file=International-Shipping-Guide-V1.docx&action=default&mobileredirect=true",
  "mime_type": "application/vnd.openxmlformats-officedocument.wordprocessingml.document",
  "size": 16177,
  "last_modified": "2026-03-17T10:26:20Z",
  "created": "2026-03-17T09:56:07Z",
  "extension": ".docx",
  "content_type": "html",
  "content": "<h1>What countries does C.E. King ship to and how long does delivery take?</h1><p>C.E. King ships worldwide from the United Kingdom. The company regularly supplies machines and spare parts to customers in over 80 countries including the United States, Canada, Europe, Middle East, Africa, Asia, and Australasia.</p><h2>Details</h2><ul><li>Machines are shipped from the UK via international freight</li><li>Spare parts ship via courier (DHL, FedEx, UPS depending on destination)</li><li>Delivery times vary: UK 1-3 days, Europe 3-7 days, USA/Canada 5-10 days, Rest of World 7-21 days (approximate)</li><li>Customers receive tracking information once goods are dispatched</li><li>Import duties and customs clearance are the responsibility of the buyer</li><li>For US customers: there is no US warehouse — all shipments come direct from the UK</li></ul><p>Link: <a href=\"https://www.ceking.com/policies/shipping-policy\">https://www.ceking.com/policies/shipping-policy</a></p>"
}